geojson_composer/__init__.py
geojson_composer/cli.py
geojson_composer/main.py
geojson_composer-0.1.5.dist-info/LICENSE
geojson_composer-0.1.5.dist-info/METADATA
geojson_composer-0.1.5.dist-info/WHEEL
geojson_composer-0.1.5.dist-info/entry_points.txt
geojson_composer-0.1.5.dist-info/top_level.txt
geojson_composer-0.1.5.dist-info/RECORD
