Metadata-Version: 2.2
Name: geojson-composer
Version: 0.1.5
Summary: A CLI tool to render GeoJSON data using Jinja2 templates.
Author: Krvss
Author-email: Stas Kravets <stas.kravets@gmail.com>
License: MIT
Requires-Python: >=3.7
License-File: LICENSE
Requires-Dist: Jinja2>=3.0
Dynamic: author
Dynamic: requires-python
